pypulse/__init__.py
pypulse/run.py
pypulse/data/BaseDataset.py
pypulse/data/CustomDataset.py
pypulse/data/ECGMIMICDataset.py
pypulse/data/PPGMIMICDataset.py
pypulse/data/PTBXLDataset.py
pypulse/data/__init__.py
pypulse/models/BaseModel.py
pypulse/models/__init__.py
pypulse/models/BRITS/BRITSModel_Wrapper.py
pypulse/models/BRITS/__init__.py
pypulse/models/BRITS/src/baseline_methods.py
pypulse/models/BRITS/src/data_loader.py
pypulse/models/BRITS/src/hyper_param.py
pypulse/models/BRITS/src/input_process.py
pypulse/models/BRITS/src/main.py
pypulse/models/BRITS/src/utils.py
pypulse/models/BRITS/src/mod_utils/brits_dataloader.py
pypulse/models/BRITS/src/models/__init__.py
pypulse/models/BRITS/src/models/brits.py
pypulse/models/BRITS/src/models/brits_i.py
pypulse/models/BRITS/src/models/gru_d.py
pypulse/models/BRITS/src/models/m_rnn.py
pypulse/models/BRITS/src/models/rits.py
pypulse/models/BRITS/src/models/rits_i.py
pypulse/models/BRITS/src/result/random_forest.py
pypulse/models/Classical/ClassicalModel_Wrapper.py
pypulse/models/Classical/FFT.py
pypulse/models/Classical/LinearInterpolation.py
pypulse/models/Classical/Mean.py
pypulse/models/Classical/__init__.py
pypulse/models/NAOMI/NAOMIModel_Wrapper.py
pypulse/models/NAOMI/__init__.py
pypulse/models/NAOMI/src/helpers.py
pypulse/models/NAOMI/src/model.py
pypulse/models/NAOMI/src/model_utils.py
pypulse/models/NAOMI/src/naomi_policy.py
pypulse/models/NAOMI/src/ptbxl.py
pypulse/models/NAOMI/src/train.py
pypulse/models/Transformer/BDCTransformer.py
pypulse/models/Transformer/Conv9Transformer.py
pypulse/models/Transformer/DeepMVITransformer.py
pypulse/models/Transformer/TransformerModel_Wrapper.py
pypulse/models/Transformer/VanillaTransformer.py
pypulse/models/Transformer/__init__.py
pypulse/models/Transformer/utils/__init__.py
pypulse/models/Transformer/utils/custom_convattn.py
pypulse/models/Transformer/utils/custom_convattn_deepmvi.py
pypulse/models/Transformer/utils/custom_convlongattn.py
sigimp-0.1.8.dist-info/LICENSE
sigimp-0.1.8.dist-info/METADATA
sigimp-0.1.8.dist-info/WHEEL
sigimp-0.1.8.dist-info/entry_points.txt
sigimp-0.1.8.dist-info/top_level.txt
sigimp-0.1.8.dist-info/RECORD
