Metadata-Version: 2.1
Name: sigimp
Version: 0.1.8
Summary: Time series imputation package
Requires-Python: >=3.7
License-File: LICENSE
Requires-Dist: fastai
Requires-Dist: tqdm
Requires-Dist: torch
Requires-Dist: numpy
Requires-Dist: scikit-learn
Requires-Dist: matplotlib
Requires-Dist: pandas
Requires-Dist: py-ecg-detectors
